flake8_import_as_module/__init__.py
flake8_import_as_module/constants.py
flake8_import_as_module/py.typed
flake8_import_as_module/utils.py
flake8_import_as_module/visitor.py
flake8_import_as_module-0.1.0.dist-info/METADATA
flake8_import_as_module-0.1.0.dist-info/entry_points.txt
flake8_import_as_module-0.1.0.dist-info/WHEEL
flake8_import_as_module-0.1.0.dist-info/LICENSE
flake8_import_as_module-0.1.0.dist-info/RECORD
