Metadata-Version: 2.1
Name: flake8-import-as-module
Version: 0.1.0
Summary: A Flake8 plugin to check if specific packages are imported as modules.
License: MIT
Keywords: flake8,linter,qa,import,flake8 plugin,code quality
Author: João Palmeiro
Author-email: joaopalmeiro@proton.me
Requires-Python: >=3.7,<4.0
Classifier: Development Status :: 4 - Beta
Classifier: Environment :: Console
Classifier: Framework :: Flake8
Classifier: Intended Audience :: Developers
Classifier: License :: OSI Approved :: MIT License
Classifier: Operating System :: OS Independent
Classifier: Programming Language :: Python :: 3
Classifier: Programming Language :: Python :: 3.7
Classifier: Programming Language :: Python :: 3.8
Classifier: Programming Language :: Python :: 3.9
Classifier: Programming Language :: Python :: 3.10
Classifier: Programming Language :: Python :: 3.11
Classifier: Programming Language :: Python :: Implementation :: CPython
Classifier: Topic :: Software Development :: Quality Assurance
Classifier: Typing :: Typed
Requires-Dist: flake8 (>=5)
